setup.py
llm_tools_5/__init__.py
llm_tools_5/instruct_fine_tune.py
llm_tools_5/instruct_fine_tune_with_rlhf.py
llm_tools_5/peft_fine_tune.py
llm_tools_5/peft_fine_tune_with_rlhf.py
llm_tools_5/pretraining.py
llm_tools_5/utils.py
llm_tools_5.egg-info/PKG-INFO
llm_tools_5.egg-info/SOURCES.txt
llm_tools_5.egg-info/dependency_links.txt
llm_tools_5.egg-info/not-zip-safe
llm_tools_5.egg-info/top_level.txt