Metadata-Version: 2.1
Name: llm-tools-5
Version: 0.1.0
Summary: LLM Fine Tuning
Author-email: sgantayat9@gmail.com
License: UNKNOWN
Platform: UNKNOWN
Requires-Python: >=3.6
